raven/__init__.py
raven/__version__.py
raven/cli.py
raven/config.py
raven/default.cfg
raven/raven.py
raven/utils.py
raven/wsgi.py
raven/data/hydrobasins_domains/hybas_lake_ar_lev01_v1c.zip
raven/data/hydrobasins_domains/hybas_lake_na_lev01_v1c.zip
raven/processes/__init__.py
raven/processes/base_xclim.py
raven/processes/wps_generic_raster_subset.py
raven/processes/wps_generic_shape_properties.py
raven/processes/wps_generic_terrain_analysis.py
raven/processes/wps_generic_zonal_stats.py
raven/processes/wps_hydrobasins_shape_selection.py
raven/processes/wps_nalcms_zonal_stats.py
raven/processes/wps_nalcms_zonal_stats_raster.py
raven/processes/wpsio.py
raven/templates/pywps.cfg
raven/testing/__init__.py
raven/testing/registry.txt
raven/testing/utils.py
raven/utilities/__init__.py
raven/utilities/analysis.py
raven/utilities/checks.py
raven/utilities/geo.py
raven/utilities/geoserver.py
raven/utilities/io.py
birdhouse_raven-0.19.0.dist-info/entry_points.txt
birdhouse_raven-0.19.0.dist-info/LICENSE
birdhouse_raven-0.19.0.dist-info/WHEEL
birdhouse_raven-0.19.0.dist-info/METADATA
birdhouse_raven-0.19.0.dist-info/RECORD
