Metadata-Version: 2.3
Name: birdhouse-raven
Version: 0.19.0
Summary: A WPS service that offers processes related to hydrological modelling.
Keywords: wps,pywps,birdhouse,raven,hydrology,gis,analysis
Author-email: David Huard <huard.david@ouranos.ca>, Richard Arsenault <richard.arsenault@etsmtl.ca>
Maintainer-email: Trevor James Smith <smith.trevorj@ouranos.ca>, Tuan Long Vu <vu.long@ouranos.ca>
Requires-Python: >=3.9.0
Classifier: Development Status :: 4 - Beta
Classifier: Intended Audience :: Developers
Classifier: Intended Audience :: Education
Classifier: Intended Audience :: Science/Research
Classifier: License :: OSI Approved :: MIT License
Classifier: Natural Language :: English
Classifier: Operating System :: MacOS :: MacOS X
Classifier: Operating System :: POSIX :: Linux
Classifier: Operating System :: Unix
Classifier: Programming Language :: Python :: 3 :: Only
Classifier: Programming Language :: Python :: 3.9
Classifier: Programming Language :: Python :: 3.10
Classifier: Programming Language :: Python :: 3.11
Classifier: Programming Language :: Python :: 3.12
Classifier: Topic :: Scientific/Engineering :: Atmospheric Science
Classifier: Topic :: Scientific/Engineering :: GIS
Classifier: Topic :: Scientific/Engineering :: Hydrology
Requires-Dist: anyascii >=0.3.2
Requires-Dist: click >=8.1.7
Requires-Dist: filelock >=3.14.1
Requires-Dist: jinja2 >=3.1.4
Requires-Dist: matplotlib
Requires-Dist: netCDF4
Requires-Dist: numpy >=1.24.0
Requires-Dist: owslib
Requires-Dist: packaging >=23.1
Requires-Dist: pandas >=2.2
Requires-Dist: psutil >=6.0.0
Requires-Dist: pywps >=4.6
Requires-Dist: requests >=2.31.0
Requires-Dist: xarray >=2023.11.0
Requires-Dist: xclim >=0.48.2
Requires-Dist: affine
Requires-Dist: cartopy >=0.23.0
Requires-Dist: fiona >=1.9.6
Requires-Dist: geojson
Requires-Dist: geopandas >=1.0
Requires-Dist: pyogrio >=0.7.2
Requires-Dist: pyproj >=3.4
Requires-Dist: rasterio
Requires-Dist: rasterstats
Requires-Dist: requests
Requires-Dist: rioxarray
Requires-Dist: shapely >=2.0
Requires-Dist: fsspec
Requires-Dist: psycopg2
Requires-Dist: pymetalink >=6.5.3
Requires-Dist: birdhouse-birdy ; extra == "dev"
Requires-Dist: black >=25.1.0 ; extra == "dev"
Requires-Dist: blackdoc >=0.3.9 ; extra == "dev"
Requires-Dist: bump-my-version >=1.2.0 ; extra == "dev"
Requires-Dist: flake8 >=7.1.1 ; extra == "dev"
Requires-Dist: flake8-rst-docstrings >=0.3.0 ; extra == "dev"
Requires-Dist: flit >=3.12,<4.0 ; extra == "dev"
Requires-Dist: ipykernel ; extra == "dev"
Requires-Dist: nbconvert ; extra == "dev"
Requires-Dist: nbval ; extra == "dev"
Requires-Dist: nc-time-axis ; extra == "dev"
Requires-Dist: numpydoc >=1.8.0 ; extra == "dev"
Requires-Dist: pip >=24.2.0 ; extra == "dev"
Requires-Dist: pooch >=1.8.0 ; extra == "dev"
Requires-Dist: pre-commit >=3.6.0 ; extra == "dev"
Requires-Dist: pytest >=8.0.0 ; extra == "dev"
Requires-Dist: pytest-cov >=5.0.0 ; extra == "dev"
Requires-Dist: pytest-xdist >=3.2 ; extra == "dev"
Requires-Dist: ruff >=0.12.0 ; extra == "dev"
Requires-Dist: tox >=4.24.1 ; extra == "dev"
Requires-Dist: yamllint >=1.35.1 ; extra == "dev"
Requires-Dist: ipyleaflet ; extra == "docs"
Requires-Dist: ipython >=8.5.0,!=9.0.0 ; extra == "docs"
Requires-Dist: ipywidgets ; extra == "docs"
Requires-Dist: nbsphinx >=0.9.5 ; extra == "docs"
Requires-Dist: sphinx >=7.0.0,<8.2.0 ; extra == "docs"
Requires-Dist: sphinx-autodoc-typehints ; extra == "docs"
Requires-Dist: sphinx-codeautolink >=0.16.2 ; extra == "docs"
Requires-Dist: sphinx-copybutton ; extra == "docs"
Requires-Dist: sphinx-rtd-theme >=1.0 ; extra == "docs"
Project-URL: About Ouranos, https://www.ouranos.ca/en/
Project-URL: Changelog, https://pavics-sdi.readthedocs.io/projects/raven/en/latest/changes.html
Project-URL: Homepage, https://pavics-raven.readthedocs.io/
Project-URL: Issue tracker, https://github.com/Ouranosinc/raven/issues
Project-URL: Source, https://github.com/Ouranosinc/raven/
Provides-Extra: dev
Provides-Extra: docs
